funky/__init__.py
funky/__main__.py
funky/app.py
funky/commands.py
funky/errors.py
funky/utils/__init__.py
funky/utils/log.py
funky/utils/xdg.py
scripts/__init__.py
scripts/install-system-dev-deps
scripts/shell/__init__.py
scripts/shell/funky.sh
pyfunky-3.5.5.dist-info/LICENSE
pyfunky-3.5.5.dist-info/METADATA
pyfunky-3.5.5.dist-info/WHEEL
pyfunky-3.5.5.dist-info/entry_points.txt
pyfunky-3.5.5.dist-info/top_level.txt
pyfunky-3.5.5.dist-info/RECORD
