Metadata-Version: 2.1
Name: pyfunky
Version: 3.5.5
Summary: Funky takes shell functions to the next level by making them easier to define, more flexible, and more interactive.
Home-page: https://github.com/bbugyi200/funky
Author: Bryan M Bugyi
Author-email: bryanbugyi34@gmail.com
License: MIT license
Keywords: funky
Platform: UNKNOWN
Classifier: Development Status :: 3 - Alpha
Classifier: Intended Audience :: Developers
Classifier: License :: OSI Approved :: MIT License
Classifier: Natural Language :: English
Classifier: Programming Language :: Python :: 3
Classifier: Programming Language :: Python :: 3.7
Classifier: Programming Language :: Python :: 3.8
Classifier: Programming Language :: Python :: 3.9
Classifier: Programming Language :: Python :: 3.10
Requires-Python: >=3.7
License-File: LICENSE
Requires-Dist: future
Requires-Dist: pygments (>=2.7.4)
Requires-Dist: six
